<?xml version="1.0" encoding="utf-8"?>
<!--DO NOT MODIFY THIS FILE.  THIS FILE IS AUTOMATICALLY GENERATED AND IS REPLACED UPON UPGRADE OR REINSTALL.--><!--Contents of this file are Copyright (C) 2001-2007 by Oracle Corporation.--><!--Consult your Oracle BI documentation for how to override messages.  Note that some or all messages may not be overriden unless your license specifically allows for it.--><WebMessageTables xmlns:sawm="com.siebel.analytics.web/message/v1"><WebMessageTable lang="en-us" system="ScorecardSystem" table="Messages">
<WebMessage name="kmsgNewScorecardChooseNewFolderName"><TEXT></TEXT></WebMessage>
<WebMessage name="kmsgNewScorecardContent"><TEXT></TEXT></WebMessage>
<WebMessage name="kmsgNewScorecardCreateNewFolder"><TEXT></TEXT></WebMessage>
<WebMessage name="kmsgNewScorecardDescription"><TEXT></TEXT></WebMessage>
<WebMessage name="kmsgNewScorecardDialogTitle"><TEXT></TEXT></WebMessage>
<WebMessage name="kmsgNewScorecardLocation"><TEXT></TEXT></WebMessage>
<WebMessage name="kmsgNewScorecardMessage"><TEXT></TEXT></WebMessage>
<WebMessage name="kmsgNewScorecardMyFolders"><TEXT></TEXT></WebMessage>
<WebMessage name="kmsgNewScorecardName"><TEXT></TEXT></WebMessage>
<WebMessage name="kmsgNewScorecardNewFolder"><TEXT></TEXT></WebMessage>
<WebMessage name="kmsgNewScorecardPerspectives"><TEXT></TEXT></WebMessage>
<WebMessage name="kmsgNewScorecardSelectFolder"><TEXT></TEXT></WebMessage>
<WebMessage name="kmsgNewScorecardSharedFolderPath"><TEXT></TEXT></WebMessage>
<WebMessage name="kmsgNewScorecardSharedFolders"><TEXT></TEXT></WebMessage>
<WebMessage name="kmsgOverwriteScorecard"><TEXT></TEXT></WebMessage>
<WebMessage name="kmsgScorecardBrowse"><TEXT></TEXT></WebMessage>
<WebMessage name="kmsgScorecardExists"><TEXT></TEXT></WebMessage>
<WebMessage name="kmsgScorecardNameRequired"><TEXT></TEXT></WebMessage>
<WebMessage name="kmsgScorecardSysPrivilegesAddAnnotationsLabel"><TEXT></TEXT></WebMessage>
<WebMessage name="kmsgScorecardSysPrivilegesCreateEditKPIsLabel"><TEXT></TEXT></WebMessage>
<WebMessage name="kmsgScorecardSysPrivilegesCreateEditMeasuresForKPILabel"><TEXT></TEXT></WebMessage>
<WebMessage name="kmsgScorecardSysPrivilegesCreateScorecardLabel"><TEXT></TEXT></WebMessage>
<WebMessage name="kmsgScorecardSysPrivilegesCreateUpdateCauseEffectLinkagesLabel"><TEXT></TEXT></WebMessage>
<WebMessage name="kmsgScorecardSysPrivilegesCreateUpdateInitiativesLabel"><TEXT></TEXT></WebMessage>
<WebMessage name="kmsgScorecardSysPrivilegesCreateUpdatePerspectivesLabel"><TEXT></TEXT></WebMessage>
<WebMessage name="kmsgScorecardSysPrivilegesCreateUpdateStrategyNodesLabel"><TEXT></TEXT></WebMessage>
<WebMessage name="kmsgScorecardSysPrivilegesCreateViewsLabel"><TEXT></TEXT></WebMessage>
<WebMessage name="kmsgScorecardSysPrivilegesOverrideAssessmentsLabel"><TEXT></TEXT></WebMessage>
<WebMessage name="kmsgScorecardSysPrivilegesPublishViewsToDashboardsLabel"><TEXT></TEXT></WebMessage>
<WebMessage name="kmsgScorecardSysPrivilegesViewScorecardLabel"><TEXT></TEXT></WebMessage>
<WebMessage name="kmsgScorecardSysPrivilegesWritebackToDatabaseForKPILabel"><TEXT></TEXT></WebMessage></WebMessageTable></WebMessageTables>
