<?xml version="1.0" encoding="utf-8"?>
<!--DO NOT MODIFY THIS FILE.  THIS FILE IS AUTOMATICALLY GENERATED AND IS REPLACED UPON UPGRADE OR REINSTALL.--><!--Contents of this file are Copyright (C) 2001-2007 by Oracle Corporation.--><!--Consult your Oracle BI documentation for how to override messages.  Note that some or all messages may not be overriden unless your license specifically allows for it.--><WebMessageTables xmlns:sawm="com.siebel.analytics.web/message/v1"><WebMessageTable lang="en-us" table="Messages" system="saw.common">
<WebMessage name="kmsgDownloadWarning"><TEXT>درخواست دانلود در حال پردازش است.</TEXT></WebMessage>
<WebMessage name="kmsgEditEvaluatePredicateEditor"><TEXT>ویرایش تابع EVALUATE_PREDICATE</TEXT></WebMessage>
<WebMessage name="kmsgFilterEditorDropdownTooltip"><TEXT>باز کردن برای انتخاب مقادیر</TEXT></WebMessage>
<WebMessage name="kmsgFlashCopyMessage"><TEXT>کپی لینک</TEXT></WebMessage>
<WebMessage name="kmsgFlashGetFlashMessage"><TEXT>Adobe Flash Player. </TEXT></WebMessage>
<WebMessage name="kmsgFlashMissingMessage"><TEXT> مورد نیاز </TEXT></WebMessage>
<WebMessage name="kmsgSaveFilterNoFiltersError"><TEXT>لفیلتری برای ذخیره کردن وجود ندارد. لطفا برای اضافه کردن فیلتر برروی گزینه  فعال کردن کلیک کنید.</TEXT></WebMessage>
<WebMessage name="kmsgSaveFilterNoPrivilege"><TEXT>شما مجوز ثبت فیلترها را ندارید</TEXT></WebMessage>
<WebMessage name="kmsgSaveFilterReplaceWithReference"><TEXT>استبدل مرشحات التقرير الحالية بمرجع للمرشح المحفوظ</TEXT></WebMessage></WebMessageTable></WebMessageTables>
